q_transformer/__init__.py
q_transformer/agent.py
q_transformer/mocks.py
q_transformer/q_learner.py
q_transformer/q_robotic_transformer.py
q_transformer/tensor_typing.py
q_transformer-0.4.5.dist-info/licenses/LICENSE
q_transformer-0.4.5.dist-info/METADATA
q_transformer-0.4.5.dist-info/WHEEL
q_transformer-0.4.5.dist-info/top_level.txt
q_transformer-0.4.5.dist-info/RECORD
